server/__inti__.py
server/__main__.py
server/server.py
mysqlconnect_mcp_server-0.1.0.dist-info/METADATA
mysqlconnect_mcp_server-0.1.0.dist-info/WHEEL
mysqlconnect_mcp_server-0.1.0.dist-info/entry_points.txt
mysqlconnect_mcp_server-0.1.0.dist-info/licenses/LICENSE.txt
mysqlconnect_mcp_server-0.1.0.dist-info/RECORD
